labreportpy/__init__.py
labreportpy/_version.py
labreportpy/version.py
labreportpy/color/__init__.py
labreportpy/color/auto_colors.py
labreportpy/color/custom_cmap.py
labreportpy/fitting/__init__.py
labreportpy/fitting/fitter.py
labreportpy/fitting/functions.py
labreportpy/io/__init__.py
labreportpy/io/print_df.py
labreportpy/io/qty_writer.py
labreportpy/io/table_writer.py
labreportpy/io/uxd_parser.py
labreportpy/utils/__init__.py
labreportpy/utils/param_fmt.py
labreportpy-0.2.0.dist-info/METADATA
labreportpy-0.2.0.dist-info/WHEEL
labreportpy-0.2.0.dist-info/licenses/LICENSE
labreportpy-0.2.0.dist-info/RECORD
